<?xml version="1.0"?>
<ArrayOfLogin xmlns:xsi="http://www.w3.org/2001/XMLSchema-instance" xmlns:xsd="http://www.w3.org/2001/XMLSchema">
  <Login>
    <UserName>Manager</UserName>
    <Password>YehuditAvigayil</Password>
    <StaffOrUser>false</StaffOrUser>
  </Login>
  <Login>
    <UserName>0944766417</UserName>
    <Password>miniProject</Password>
    <StaffOrUser>false</StaffOrUser>
    <profileSource>C:\Users\Hudis\source\repos\HudiF\DotNet5782_9033_6996\PL\Icons\bbchedva whatsapp.jpeg</profileSource>
  </Login>
  <Login>
    <UserName>0231694393</UserName>
    <Password>miniProject</Password>
    <StaffOrUser>false</StaffOrUser>
    <profileSource>C:\Users\Hudis\source\repos\HudiF\DotNet5782_9033_6996\PL\Icons\bbchedva whatsapp.jpeg</profileSource>
  </Login>
  <Login>
    <UserName>0589287323</UserName>
    <Password>miniProject</Password>
    <StaffOrUser>false</StaffOrUser>
    <profileSource>C:\Users\Hudis\source\repos\HudiF\DotNet5782_9033_6996\PL\Icons\bbchedva whatsapp.jpeg</profileSource>
  </Login>
  <Login>
    <UserName>0683362721</UserName>
    <Password>miniProject</Password>
    <StaffOrUser>false</StaffOrUser>
    <profileSource>C:\Users\Hudis\source\repos\HudiF\DotNet5782_9033_6996\PL\Icons\bbchedva whatsapp.jpeg</profileSource>
  </Login>
  <Login>
    <UserName>0980778723</UserName>
    <Password>miniProject</Password>
    <StaffOrUser>false</StaffOrUser>
    <profileSource>C:\Users\Hudis\source\repos\HudiF\DotNet5782_9033_6996\PL\Icons\bbchedva whatsapp.jpeg</profileSource>
  </Login>
  <Login>
    <UserName>0753284757</UserName>
    <Password>miniProject</Password>
    <StaffOrUser>false</StaffOrUser>
    <profileSource>C:\Users\Hudis\source\repos\HudiF\DotNet5782_9033_6996\PL\Icons\bbchedva whatsapp.jpeg</profileSource>
  </Login>
  <Login>
    <UserName>0290111002</UserName>
    <Password>miniProject</Password>
    <StaffOrUser>false</StaffOrUser>
    <profileSource>C:\Users\Hudis\source\repos\HudiF\DotNet5782_9033_6996\PL\Icons\bbchedva whatsapp.jpeg</profileSource>
  </Login>
  <Login>
    <UserName>0366535232</UserName>
    <Password>miniProject</Password>
    <StaffOrUser>false</StaffOrUser>
    <profileSource>C:\Users\Hudis\source\repos\HudiF\DotNet5782_9033_6996\PL\Icons\bbchedva whatsapp.jpeg</profileSource>
  </Login>
  <Login>
    <UserName>0441874236</UserName>
    <Password>miniProject</Password>
    <StaffOrUser>false</StaffOrUser>
    <profileSource>C:\Users\Hudis\source\repos\HudiF\DotNet5782_9033_6996\PL\Icons\bbchedva whatsapp.jpeg</profileSource>
  </Login>
  <Login>
    <UserName>0445313969</UserName>
    <Password>miniProject</Password>
    <StaffOrUser>false</StaffOrUser>
    <profileSource>C:\Users\Hudis\source\repos\HudiF\DotNet5782_9033_6996\PL\Icons\bbchedva whatsapp.jpeg</profileSource>
  </Login>
</ArrayOfLogin>